didabox/__init__.py
didabox/check.py
didabox/info.py
didabox/login.py
didabox/main.py
didabox/pomodoros.py
didabox/request.py
didabox/task.py
didabox/utils.py
didabox-3.3.0.dist-info/LICENSE
didabox-3.3.0.dist-info/METADATA
didabox-3.3.0.dist-info/WHEEL
didabox-3.3.0.dist-info/RECORD
